{
    "frames": {
        "2.png": {
            "frame": {
                "x": 0,
                "y": 0,
                "w": 3,
                "h": 7
            },
            "rotated": false,
            "trimmed": false,
            "spriteSourceSize": {
                "x": 0,
                "y": 0,
                "w": 3,
                "h": 7
            },
            "sourceSize": {
                "w": 3,
                "h": 7
            }
        },
        "3.png": {
            "frame": {
                "x": 3,
                "y": 0,
                "w": 3,
                "h": 7
            },
            "rotated": false,
            "trimmed": false,
            "spriteSourceSize": {
                "x": 0,
                "y": 0,
                "w": 3,
                "h": 7
            },
            "sourceSize": {
                "w": 3,
                "h": 7
            }
        },
        "4.png": {
            "frame": {
                "x": 6,
                "y": 0,
                "w": 5,
                "h": 7
            },
            "rotated": false,
            "trimmed": false,
            "spriteSourceSize": {
                "x": 0,
                "y": 0,
                "w": 5,
                "h": 7
            },
            "sourceSize": {
                "w": 5,
                "h": 7
            }
        },
        "5.png": {
            "frame": {
                "x": 11,
                "y": 0,
                "w": 7,
                "h": 7
            },
            "rotated": false,
            "trimmed": false,
            "spriteSourceSize": {
                "x": 0,
                "y": 0,
                "w": 7,
                "h": 7
            },
            "sourceSize": {
                "w": 7,
                "h": 7
            }
        },
        "6.png": {
            "frame": {
                "x": 18,
                "y": 0,
                "w": 9,
                "h": 7
            },
            "rotated": false,
            "trimmed": false,
            "spriteSourceSize": {
                "x": 0,
                "y": 0,
                "w": 9,
                "h": 7
            },
            "sourceSize": {
                "w": 9,
                "h": 7
            }
        },
        "8.png": {
            "frame": {
                "x": 27,
                "y": 0,
                "w": 9,
                "h": 7
            },
            "rotated": false,
            "trimmed": false,
            "spriteSourceSize": {
                "x": 0,
                "y": 0,
                "w": 9,
                "h": 7
            },
            "sourceSize": {
                "w": 9,
                "h": 7
            }
        },
        "9.png": {
            "frame": {
                "x": 36,
                "y": 0,
                "w": 7,
                "h": 7
            },
            "rotated": false,
            "trimmed": false,
            "spriteSourceSize": {
                "x": 0,
                "y": 0,
                "w": 7,
                "h": 7
            },
            "sourceSize": {
                "w": 7,
                "h": 7
            }
        },
        "10.png": {
            "frame": {
                "x": 43,
                "y": 0,
                "w": 7,
                "h": 7
            },
            "rotated": false,
            "trimmed": false,
            "spriteSourceSize": {
                "x": 0,
                "y": 0,
                "w": 7,
                "h": 7
            },
            "sourceSize": {
                "w": 7,
                "h": 7
            }
        },
        "11.png": {
            "frame": {
                "x": 50,
                "y": 0,
                "w": 7,
                "h": 7
            },
            "rotated": false,
            "trimmed": false,
            "spriteSourceSize": {
                "x": 0,
                "y": 0,
                "w": 7,
                "h": 7
            },
            "sourceSize": {
                "w": 7,
                "h": 7
            }
        },
        "12.png": {
            "frame": {
                "x": 57,
                "y": 0,
                "w": 7,
                "h": 7
            },
            "rotated": false,
            "trimmed": false,
            "spriteSourceSize": {
                "x": 0,
                "y": 0,
                "w": 7,
                "h": 7
            },
            "sourceSize": {
                "w": 7,
                "h": 7
            }
        },
        "brick-icon.png": {
            "frame": {
                "x": 64,
                "y": 0,
                "w": 7,
                "h": 7
            },
            "rotated": false,
            "trimmed": false,
            "spriteSourceSize": {
                "x": 0,
                "y": 0,
                "w": 7,
                "h": 7
            },
            "sourceSize": {
                "w": 7,
                "h": 7
            }
        },
        "brick.png": {
            "frame": {
                "x": 71,
                "y": 0,
                "w": 33,
                "h": 28
            },
            "rotated": false,
            "trimmed": false,
            "spriteSourceSize": {
                "x": 0,
                "y": 0,
                "w": 33,
                "h": 28
            },
            "sourceSize": {
                "w": 33,
                "h": 28
            }
        },
        "city.png": {
            "frame": {
                "x": 104,
                "y": 0,
                "w": 6,
                "h": 7
            },
            "rotated": false,
            "trimmed": false,
            "spriteSourceSize": {
                "x": 0,
                "y": 0,
                "w": 6,
                "h": 7
            },
            "sourceSize": {
                "w": 6,
                "h": 7
            }
        },
        "desert.png": {
            "frame": {
                "x": 110,
                "y": 0,
                "w": 33,
                "h": 28
            },
            "rotated": false,
            "trimmed": false,
            "spriteSourceSize": {
                "x": 0,
                "y": 0,
                "w": 33,
                "h": 28
            },
            "sourceSize": {
                "w": 33,
                "h": 28
            }
        },
        "die-1.png": {
            "frame": {
                "x": 143,
                "y": 0,
                "w": 9,
                "h": 9
            },
            "rotated": false,
            "trimmed": false,
            "spriteSourceSize": {
                "x": 0,
                "y": 0,
                "w": 9,
                "h": 9
            },
            "sourceSize": {
                "w": 9,
                "h": 9
            }
        },
        "die-2.png": {
            "frame": {
                "x": 152,
                "y": 0,
                "w": 9,
                "h": 9
            },
            "rotated": false,
            "trimmed": false,
            "spriteSourceSize": {
                "x": 0,
                "y": 0,
                "w": 9,
                "h": 9
            },
            "sourceSize": {
                "w": 9,
                "h": 9
            }
        },
        "die-3.png": {
            "frame": {
                "x": 161,
                "y": 0,
                "w": 9,
                "h": 9
            },
            "rotated": false,
            "trimmed": false,
            "spriteSourceSize": {
                "x": 0,
                "y": 0,
                "w": 9,
                "h": 9
            },
            "sourceSize": {
                "w": 9,
                "h": 9
            }
        },
        "die-4.png": {
            "frame": {
                "x": 170,
                "y": 0,
                "w": 9,
                "h": 9
            },
            "rotated": false,
            "trimmed": false,
            "spriteSourceSize": {
                "x": 0,
                "y": 0,
                "w": 9,
                "h": 9
            },
            "sourceSize": {
                "w": 9,
                "h": 9
            }
        },
        "die-5.png": {
            "frame": {
                "x": 179,
                "y": 0,
                "w": 9,
                "h": 9
            },
            "rotated": false,
            "trimmed": false,
            "spriteSourceSize": {
                "x": 0,
                "y": 0,
                "w": 9,
                "h": 9
            },
            "sourceSize": {
                "w": 9,
                "h": 9
            }
        },
        "die-6.png": {
            "frame": {
                "x": 188,
                "y": 0,
                "w": 9,
                "h": 9
            },
            "rotated": false,
            "trimmed": false,
            "spriteSourceSize": {
                "x": 0,
                "y": 0,
                "w": 9,
                "h": 9
            },
            "sourceSize": {
                "w": 9,
                "h": 9
            }
        },
        "house.png": {
            "frame": {
                "x": 197,
                "y": 0,
                "w": 6,
                "h": 5
            },
            "rotated": false,
            "trimmed": false,
            "spriteSourceSize": {
                "x": 0,
                "y": 0,
                "w": 6,
                "h": 5
            },
            "sourceSize": {
                "w": 6,
                "h": 5
            }
        },
        "number-tile.png": {
            "frame": {
                "x": 203,
                "y": 0,
                "w": 11,
                "h": 11
            },
            "rotated": false,
            "trimmed": false,
            "spriteSourceSize": {
                "x": 0,
                "y": 0,
                "w": 11,
                "h": 11
            },
            "sourceSize": {
                "w": 11,
                "h": 11
            }
        },
        "road-flat.png": {
            "frame": {
                "x": 214,
                "y": 0,
                "w": 9,
                "h": 4
            },
            "rotated": false,
            "trimmed": false,
            "spriteSourceSize": {
                "x": 0,
                "y": 0,
                "w": 9,
                "h": 4
            },
            "sourceSize": {
                "w": 9,
                "h": 4
            }
        },
        "road-left.png": {
            "frame": {
                "x": 223,
                "y": 0,
                "w": 7,
                "h": 8
            },
            "rotated": false,
            "trimmed": false,
            "spriteSourceSize": {
                "x": 0,
                "y": 0,
                "w": 7,
                "h": 8
            },
            "sourceSize": {
                "w": 7,
                "h": 8
            }
        },
        "road-right.png": {
            "frame": {
                "x": 230,
                "y": 0,
                "w": 7,
                "h": 8
            },
            "rotated": false,
            "trimmed": false,
            "spriteSourceSize": {
                "x": 0,
                "y": 0,
                "w": 7,
                "h": 8
            },
            "sourceSize": {
                "w": 7,
                "h": 8
            }
        },
        "sheep-icon.png": {
            "frame": {
                "x": 237,
                "y": 0,
                "w": 7,
                "h": 7
            },
            "rotated": false,
            "trimmed": false,
            "spriteSourceSize": {
                "x": 0,
                "y": 0,
                "w": 7,
                "h": 7
            },
            "sourceSize": {
                "w": 7,
                "h": 7
            }
        },
        "sheep.png": {
            "frame": {
                "x": 244,
                "y": 0,
                "w": 33,
                "h": 28
            },
            "rotated": false,
            "trimmed": false,
            "spriteSourceSize": {
                "x": 0,
                "y": 0,
                "w": 33,
                "h": 28
            },
            "sourceSize": {
                "w": 33,
                "h": 28
            }
        },
        "stone-icon.png": {
            "frame": {
                "x": 277,
                "y": 0,
                "w": 7,
                "h": 7
            },
            "rotated": false,
            "trimmed": false,
            "spriteSourceSize": {
                "x": 0,
                "y": 0,
                "w": 7,
                "h": 7
            },
            "sourceSize": {
                "w": 7,
                "h": 7
            }
        },
        "stone.png": {
            "frame": {
                "x": 284,
                "y": 0,
                "w": 33,
                "h": 28
            },
            "rotated": false,
            "trimmed": false,
            "spriteSourceSize": {
                "x": 0,
                "y": 0,
                "w": 33,
                "h": 28
            },
            "sourceSize": {
                "w": 33,
                "h": 28
            }
        },
        "wheat-icon.png": {
            "frame": {
                "x": 317,
                "y": 0,
                "w": 7,
                "h": 7
            },
            "rotated": false,
            "trimmed": false,
            "spriteSourceSize": {
                "x": 0,
                "y": 0,
                "w": 7,
                "h": 7
            },
            "sourceSize": {
                "w": 7,
                "h": 7
            }
        },
        "wheat.png": {
            "frame": {
                "x": 324,
                "y": 0,
                "w": 33,
                "h": 28
            },
            "rotated": false,
            "trimmed": false,
            "spriteSourceSize": {
                "x": 0,
                "y": 0,
                "w": 33,
                "h": 28
            },
            "sourceSize": {
                "w": 33,
                "h": 28
            }
        },
        "wood-icon.png": {
            "frame": {
                "x": 357,
                "y": 0,
                "w": 7,
                "h": 7
            },
            "rotated": false,
            "trimmed": false,
            "spriteSourceSize": {
                "x": 0,
                "y": 0,
                "w": 7,
                "h": 7
            },
            "sourceSize": {
                "w": 7,
                "h": 7
            }
        },
        "wood.png": {
            "frame": {
                "x": 364,
                "y": 0,
                "w": 33,
                "h": 28
            },
            "rotated": false,
            "trimmed": false,
            "spriteSourceSize": {
                "x": 0,
                "y": 0,
                "w": 33,
                "h": 28
            },
            "sourceSize": {
                "w": 33,
                "h": 28
            }
        }
    },
    "animations": {
        "die": [
            "die-1.png",
            "die-2.png",
            "die-3.png",
            "die-4.png",
            "die-5.png",
            "die-6.png"
        ]
    },
    "meta": {
        "app": "https://www.codeandweb.com/texturepacker",
        "version": "1.1",
        "image": "assets.png",
        "format": "RGBA8888",
        "size": {
            "w": 397,
            "h": 28
        },
        "scale": "1",
        "smartupdate": "$TexturePacker:SmartUpdate:0a42007f4e75b91cf1c0906cf8c4d032:3427547d9267f8f859980f681252db7a:a759b6bbc8381ac9c472b28f589ad0d6$"
    }
}